colorconsole99/colorconsole99.py
colorconsole99-1.0.1.1.dist-info/METADATA
colorconsole99-1.0.1.1.dist-info/WHEEL
colorconsole99-1.0.1.1.dist-info/top_level.txt
colorconsole99-1.0.1.1.dist-info/RECORD
