Metadata-Version: 2.1
Name: colorconsole99
Version: 1.0.1.1
Summary: A python library that displays symbols in front of command line text
Home-page: https://github.com/windows99-hue/colorconsole99
Author: Kaihan Zhang 张凯涵
Author-email: 3013907412@qq.com
License: MIT License
Keywords: colorconsole
Platform: UNKNOWN
Requires-Dist: colorama
